pymesos/__init__.py
pymesos/detector.py
pymesos/executor.py
pymesos/interface.py
pymesos/operator_v1.py
pymesos/process.py
pymesos/scheduler.py
pymesos/utils.py
pymesos/zkpython.py
pymesos/subprocess/__init__.py
pymesos/subprocess/executor.py
pymesos/subprocess/popen.py
pymesos/subprocess/scheduler.py
toil_pymesos-0.3.80.dist-info/LICENSE
toil_pymesos-0.3.80.dist-info/METADATA
toil_pymesos-0.3.80.dist-info/WHEEL
toil_pymesos-0.3.80.dist-info/top_level.txt
toil_pymesos-0.3.80.dist-info/RECORD
